nanoyc/logging/__init__.py
nanoyc_logging-0.1.0.dist-info/LICENSE.txt
nanoyc_logging-0.1.0.dist-info/METADATA
nanoyc_logging-0.1.0.dist-info/WHEEL
nanoyc_logging-0.1.0.dist-info/top_level.txt
nanoyc_logging-0.1.0.dist-info/RECORD
