Metadata-Version: 2.1
Name: nanoyc-logging
Version: 0.1.0
Summary: A nano package for working with Yandex Cloud
Author: Dima Frolenko
Author-email: orangefrol@gmail.com
License: LICENSE.txt
License-File: LICENSE.txt
Requires-Dist: importlib
Requires-Dist: json
